legitcli/command/__init__.py
legitcli/flows/__init__.py
legitcli/flows/help.py
legitcli/flows/init.py
legitcli/flows/README.md
legitcli/flows/validate.py
legitcli/flows/version.py
legitcli/git/client.py
legitcli/git/README.md
legitcli/main.py
legitcli/model/annotations.py
legitcli/model/bindings.py
legitcli/model/config.py
legitcli/model/constants.py
legitcli/model/exceptions.py
legitcli/model/globals.py
legitcli/model/README.md
legitcli/model/rules.py
legitcli/model/ruleset.py
legitcli/model/scope_conditions.py
legitcli/model/validator_results.py
legitcli/parsing/__init__.py
legitcli/parsing/converters/base_converter.py
legitcli/parsing/converters/config_converter.py
legitcli/parsing/converters/dynamic/__init__.py
legitcli/parsing/converters/legit_rules_converter.py
legitcli/parsing/converters/rule_converter.py
legitcli/parsing/converters/scope_condition_converter.py
legitcli/parsing/converters/scoped_ruleset_converter.py
legitcli/parsing/README.md
legitcli/typeutils/guards.py
legitcli/utils/lazy.py
legitcli/utils/string.py
legitcli/validator/__init__.py
legitcli/validator/commit.py
legitcli/validator/generic.py
legitcli/validator/README.md
legitcli/validator/rules/__init__.py
legitcli/validator/ruleset.py
legitcli/validator/scopes/__init__.py
legitcli-0.1.7.dist-info/AUTHORS.txt
legitcli-0.1.7.dist-info/entry_points.txt
legitcli-0.1.7.dist-info/LICENSE.txt
legitcli-0.1.7.dist-info/METADATA
legitcli-0.1.7.dist-info/WHEEL
legitcli-0.1.7.dist-info/RECORD
